{"css":"","framework":"duck-10.0.0","title":"Ajuda Pages","build_id":"578da4d2680ce2cc01dc3943","icon":"..\/GlobalArt\/AppIconDefault_PagesP4.png","sections":{"tan724868a9":{"name":"Nocions bàsiques sobre el Pages","children":["tane9d8593b0","tan85812a11d","tancdeedb11c","tana8e1c6523","tanf610b45cf","tana7e101d4c","tan95caaa4ff","tan4d7be9bf0","tancfc4d5c02","tan0b239532d","tan72488052","apdbf006d058e084"]},"apd1fecf1f832024":{"name":"Canviar l’aspecte d’una taula","children":["tana77607537","tanb8470373a","tanc80345ef4","tan6698de8db"]},"tan31021e168":{"name":"Crear taules i gràfics","children":["tan479427c3b","tane436a31d7","tan807495cac"]},"apd0f0768c618e24":{"name":"Donar format als caràcters i signes de puntuació","children":["tanc87eaca89","tanec2c2fdfd","tan4745152e4","tan7aaef6765","tanad45f9cce","tanfbd4156e"]},"apda2b77ab341d24":{"name":"Canviar l’aspecte dels objectes","children":["tane985ef30f","tana91415979","tan14a575e90","tan0f46b6d67","tan8728fa657"]},"tan479427c3b":{"name":"Crear i modificar taules","children":["tan0c9e54229","tan661e2f40a","apd7f4b6a05c1fb4","tanc388a772c","tan3af7438f2","taneef63d4fa","apd97f28179efcc4","tan407430bc2","apd1fecf1f832024","tand4b4df5c5"]},"apd285ff6540c5a4":{"name":"Transferir documents entre un Mac i un dispositiu iOS","children":["tanc2dcd8bf5","tanb5b5c055","tand51dba2c"]},"tanbac64b599":{"name":"Col·laborar amb altres persones","children":["tane08d39674","tan1b320e5a8","tan227ad0c21","tan6df85201f","tanbe5d4e9dd"]},"tan8db5c78ee":{"name":"Solució de problemes","children":["tanca2e6d185","tandbcfe3f68","tan5dce57d64"]},"tanf3da59072":{"name":"Utilitzar estils de paràgraf","children":["tanaa39b0aa3","tan2a4a61fcf","tanc48ac66bd","tan42d243e76","tanb8c18c476"]},"apd97f28179efcc4":{"name":"Donar format a les dades d’una cel·la de taula","children":["tan0e0aa7b51","tan090042718","tan4624573aa","tan1c959548d","tan3ac4e1b94"]},"tan6f1b71c79":{"name":"Dreceres de teclat","children":["tanc0ffef022","tan014c3bd19"]},"apd50e728d33d044":{"name":"Parts d’un document","children":["tan04071ed64","tan5b8c588d6","tan0e6bf8310","tanbb3f4cb"]},"apd7c954dc37f864":{"name":"Tabuladors i alineació del text","children":["tan39ebf390a","tanafea6d099","tanea6d0807d"]},"apdbf006d058e084":{"name":"Personalitzar l’aplicació","children":["tan484d10397","tanafa2f718a","tan0870f78aa","tan2f9dbf1d8","tanfc38d7da0"]},"tane436a31d7":{"name":"Afegir fórmules i funcions","children":["tana41710df7","tanc121c3e2e","tane76a3f8cb","tan0fb3b3e0e"]},"tan0fb3b3e0e":{"name":"Operadors de cadena i caràcters comodí a les fórmules","children":["tan7132f4c15","tan3c62ca531"]},"tanef67246f0":{"name":"Afegir imatges, formes i contingut multimèdia","children":["tanc422178d0","tand6205cf6d","tanb3bc78786","tan9ad18c384","tana3148ea61","tan785873ed3","tan9fdc65243","apda2b77ab341d24","tan114930688","tandb043f1ca","apd4b13abcb71e34"]},"tan4b2974058":{"name":"Gestionar documents","children":["tance1161f26","tan7f1de6ec5","tandb9f7c3b0","tan1aa688b36","tan9efdf9906","tanca246d3ac","tanb343cb739","apd285ff6540c5a4"]},"apd70917834f6444":{"name":"Utilitzar eines d’escriptura i d’edició","children":["tanf3d8c3e49","tan9ef3ea9f8","tan72486d0d","tanca15d8a79","tand47165437"]},"apde9a9db688b444":{"name":"Afegir i editar text","children":["tane185bcdb9","tan6f943622b","tan59042a403","tan567457616"]},"tan33e8694":{"name":"Editar text","children":["apde9a9db688b444","tan7248a6ec","tanf3da59072","apd0f0768c618e24","taned4110e43","tan724896ee","tanf709cafed","tand51db403","apd70917834f6444"]},"tan33e8ab5":{"name":"Formatar documents","children":["tan249e04269","tan8f54dbbd9","apd50e728d33d044","tan7248753e","tan92235a2d6","tan45b66cbe7","apd7c954dc37f864","tand23f7b5d7","tan322bf978a","tan2756f11a7","tan802e88b40","tan526e83fd0","tan68ca2d25c"]},"tan807495cac":{"name":"Crear i modificar gràfics","children":["tanb07e899b3","tan365bd1dea","tanbb81779d8","tan5836bce3d","tana5ac9c5ea","tan8ba5fdcfc","tan8ba5fdcfa","tanece59000a","tan532dc7442"]},"tan7248a6ec":{"name":"Canviar l’aspecte del text","children":["tane4dc5cd05","tanf69e05015","tanc25de311d","tanf5aeecaba","tan3b05a865e"]},"apd7f4b6a05c1fb4":{"name":"Afegir o canviar files i columnes de taula","children":["tanc921265e9","tana511f116b","tane5bb1a9b6"]},"apd4b13abcb71e34":{"name":"Col·locar objectes en una pàgina","children":["tanc9ead56b9","tan5e2833bf7","tan5eab46568"]},"tan33e8c48":{"name":"Compartir i col·laborar","children":["tan79be8e93","tanbac64b599","tan2685b84ff","tancde3b34f","tan6704f1b0f","tan78c0ddfdb"]}},"birdseed_version":5,"toc":["tan724868a9","tan33e8694","tan33e8ab5","tanef67246f0","tan31021e168","tan4b2974058","tan33e8c48","tan8db5c78ee","tan6f1b71c79"],"locale":"ca","version":"6.0","enable_tracking":false,"source_schema":"apd-schema","platform":"mac","build_date":"2016.07.18-21:04:36","landing":"tan72790870","product":"pages","urls":{},"copyright":"tana34daa50","show_previous_next":false,"topics":{"tana511f116b":{"name":"Moure les files i columnes d’una taula"},"tanfa7f58f9c":{"name":"Definir estils per a les sèries de dades","href":"tanfa7f58f9c.html"},"tan04071ed64":{"name":"Seccions de format","searchName":"Formatar seccions en un document del Pages"},"tanc0ffef022":{"name":"Dreceres de teclat del Pages per a Mac","searchName":"Dreceres de teclat del Pages per a Mac"},"tand51db403":{"name":"Afegir enllaços","searchName":"Afegir enllaços en un document del Pages"},"tana77607537":{"name":"Canviar l’aspecte del text de les taules","searchName":"Canviar l’aspecte del text d’una taula al Pages"},"tana9c1d5c2e":{"name":"gestor de documents","categories":["aside"]},"tan0b239532d":{"name":"Imprimir un document o un sobre","searchName":"Imprimir un document o un sobre al Pages"},"tan9ef3ea9f8":{"name":"Buscar paraules","searchName":"Buscar paraules al diccionari en un document del Pages"},"tan9ad18c384":{"name":"Formes","searchName":"Afegir i editar formes en un document del Pages"},"tanca2e6d185":{"name":"Si no podeu afegir o eliminar una pàgina","searchName":"Si no podeu afegir o eliminar una pàgina en un document del Pages"},"tanad45f9cce":{"name":"Donar format als guionets, guions i cometes","searchName":"Formatar guions i cometes en un document del Pages"},"tanaa39b0aa3":{"name":"Visió general dels estils de paràgraf","searchName":"Visió general dels estils de paràgraf del Pages"},"tanb5b5c055":{"name":"Amb l’iTunes","searchName":"Utilitzar l’iTunes per transferir arxius al Pages"},"tan2756f11a7":{"name":"Convertir un document de processament de text o de disposició de pàgina"},"tan526e83fd0":{"name":"Crear una plantilla personalitzada","searchName":"Crear una plantilla del Pages personalitzada"},"tanb8c18c476":{"name":"Utilitzar una drecera de teclat per aplicar un estil","searchName":"Utilitzar una drecera de teclat per aplicar un estil en un document del Pages"},"tana5ac9c5ea":{"name":"Modificar dades d’un gràfic","searchName":"Modificar referències de dades d’un gràfic al Pages"},"tancde3b34f":{"name":"Afegir comentaris i ressaltar text","searchName":"Afegir comentaris i ressaltar text en un document del Pages"},"tan72790870":{"name":"Ajuda Pages","href":"tan72790870.html","categories":["landing"]},"tan249e04269":{"name":"Ajustar la mida del paper i els marges","searchName":"Ajustar la mida del paper i els marges en un document del Pages"},"tan59042a403":{"name":"Utilitzar el dictat per introduir text","searchName":"Dictar text en un document del Pages"},"tance1161f26":{"name":"Exportar com a PDF o en un altre format d’arxiu","searchName":"Exportar un document del Pages com un arxiu PDF o en un altre format d’arxiu"},"tan7132f4c15":{"name":"Maneres d’utilitzar l’operador de cadena i els comodins","searchName":"Maneres d’utilitzar l’operador de cadena i els comodins al Pages"},"tan5b8c588d6":{"name":"Afegir una taula de contingut","searchName":"Afegir una taula de contingut a un document del Pages"},"tan0870f78aa":{"name":"Mostrar o ocultar les barres laterals","searchName":"Mostrar o ocultar les barres laterals al Pages"},"tan8728fa657":{"name":"Utilitzar els estils d’objecte","searchName":"Utilitzar estils d’objecte en un document del Pages"},"tanc121c3e2e":{"name":"Formatar una equació amb el MathType","searchName":"Formatar una equació al Pages amb el MathType"},"tanbdd1704fc":{"name":"Majúscules + Arrossegar","categories":["aside"]},"tan4624573aa":{"name":"Ajustar el text per cabre a una cel·la de taula","searchName":"Ajustar el text d’una cel·la de taula al Pages"},"tanc25de311d":{"name":"Canviar el color del text","searchName":"Canviar el color del text en un document del Pages"},"tan407430bc2":{"name":"Ordenar alfabèticament o ordenar dades en una taula","searchName":"Ordenar alfabèticament o ordenar dades en una taula del Pages"},"tan322bf978a":{"name":"Veure els símbols de format i la disposició","searchName":"Veure els símbols de format i la disposició en un document del Pages"},"tan6f943622b":{"name":"Copiar i enganxar text","searchName":"Copiar i enganxar text en un document del Pages"},"tan3b05a865e":{"name":"Afegir una ombra o un contorn al text","searchName":"Afegir una ombra o un contorn al text en un document del Pages"},"tane4dc5cd05":{"name":"Canviar el tipus de lletra o la mida de lletra","searchName":"Canviar el tipus de lletra o la mida de la lletra en un document del Pages"},"tan0f46b6d67":{"name":"Afegir una reflexió o una ombra","searchName":"Afegir un reflex o una ombra a un objecte en un document del Pages"},"tan2685b84ff":{"name":"Utilitzar el control de canvis","searchName":"Controlar els canvis en un document del Pages"},"tanca246d3ac":{"name":"Protegir un document amb contrasenya","searchName":"Protegir amb contrasenya un document del Pages"},"tand6205cf6d":{"name":"Col·locar objectes amb text","searchName":"Col·locar objectes amb text en un document del Pages"},"tanf5aeecaba":{"name":"Canviar les majúscules del text","searchName":"Canviar l’ús de majúscules del text en un document del Pages"},"tan724896ee":{"name":"Donar format a les llistes","searchName":"Formatar llistes en un document del Pages"},"tan8ba5fdcfc":{"name":"Canviar l’aspecte del text i les etiquetes d’un gràfic","searchName":"Canviar l’aspecte del text i les etiquetes d’un gràfic al Pages"},"tan68ca2d25c":{"name":"Imprimir targetes de visita i etiquetes","searchName":"Imprimir sobres, etiquetes i targetes de visita amb el Pages"},"tanfc38d7da0":{"name":"Definir una plantilla per omissió","searchName":"Especificar una plantilla per omissió per als documents del Pages"},"tane1af15b59":{"name":"estil de caràcter","categories":["aside"]},"tan79be8e93":{"name":"Utilitzar l’iCloud amb el Pages"},"tanafea6d099":{"name":"Alinear text","searchName":"Alinear text en un document del Pages"},"tanb343cb739":{"name":"Instal·lar i gestionar les plantilles de document","searchName":"Instal·lar i gestionar les plantilles del Pages"},"tan14a575e90":{"name":"Afegir o canviar vores","searchName":"Afegir o canviar vores d’objectes en un document del Pages"},"tan0cdb8295c":{"name":"Ordre + clic","categories":["aside"]},"tane76a3f8cb":{"name":"Tipus d’arguments i valors","searchName":"Tipus d’arguments i valors de les funcions al Pages"},"tanf7f4944f3":{"name":"desbloquejar un objecte","categories":["aside"]},"tana7e101d4c":{"name":"Desfer o refer canvis","searchName":"Desfer o refer canvis en un document del Pages"},"tanfb6165d15":{"name":"versió del programari iOS","categories":["aside"]},"tandb9f7c3b0":{"name":"Traslladar un document","searchName":"Traslladar un document del Pages"},"tan2f9dbf1d8":{"name":"Configurar les preferències del Pages"},"tane185bcdb9":{"name":"Afegir text","searchName":"Afegir text en un document del Pages"},"tan090042718":{"name":"Crear un format personalitzat de cel·la de taula","searchName":"Crear un format personalitzat de cel·la de taula al Pages"},"tan95caaa4ff":{"name":"Desar i canviar el nom d’un document","searchName":"Desar i canviar el nom d’un document del Pages"},"tan2a4a61fcf":{"name":"Aplicar un estil de paràgraf","searchName":"Aplicar un estil de paràgraf en un document del Pages"},"tane08d39674":{"name":"Visió general de la col·laboració","searchName":"Visió general de la col·laboració al Pages"},"tanbe5d4e9dd":{"name":"Deixar de compartir un document","searchName":"Deixar de compartir un document del Pages"},"tan22c7165c6":{"name":"Navegadors compatibles per a la col·laboració","categories":["aside"]},"tan9fdc65243":{"name":"Marques d’aigua i objectes de fons","searchName":"Afegir marques d’aigua i objectes de fons en un document del Pages"},"tan4e7a14f21":{"name":"comodins","categories":["aside"]},"tana0e75ec37":{"name":"ID d’Apple","categories":["aside"]},"tan45b66cbe7":{"name":"Regles","searchName":"Utilitzar regles en un document del Pages"},"tan484d10397":{"name":"Aplicar un zoom a un document o veure el Pages a pantalla completa"},"tan661e2f40a":{"name":"Seleccionar taules, cel·les, files i columnes","searchName":"Seleccionar taules, cel·les, files i columnes al Pages"},"tand51dba2c":{"name":"Amb un servidor WebDAV","searchName":"Utilitzar un servidor WebDAV per desar documents del Pages"},"tan5dce57d64":{"name":"Si no trobeu un botó o un control esmentat a l’Ajuda Pages"},"tan0e0aa7b51":{"name":"Donar format als tipus de dades","searchName":"Donar format a les cel·les de taula del Pages per mostrar diferents tipus de dades "},"tan567457616":{"name":"Introduir text en un altre idioma","searchName":"Introduir text en un altre idioma al Pages"},"tan85812a11d":{"name":"Crear un document","searchName":"Crear un document nou del Pages"},"tanacf8462a1":{"name":"estil de paràgraf","categories":["aside"]},"tan2a6f1039a":{"name":"Explorador de funcions","categories":["aside"]},"tan647efa076":{"name":"marcador de posició multimèdia","categories":["aside"]},"tana8e1c6523":{"name":"Tancar un document"},"tane985ef30f":{"name":"Canviar la transparència","searchName":"Canviar la transparència d’una imatge, forma, quadre de text, línia, fletxa o vídeo en un document del Pages"},"tanfbd4156e":{"name":"Formatar text xinès, japonès o coreà","searchName":"Formatar text xinès, japonès o coreà en un document del Pages"},"tanc6ea89c7b":{"name":"Seleccionar files o columnes senceres","categories":["aside"]},"tan90d2d0343":{"name":"Seleccionar una taula","categories":["aside"]},"tanab867d20b":{"name":"AirDrop","categories":["aside"]},"tanc17fc8f49":{"name":"iCloud Drive","categories":["aside"]},"tanca15d8a79":{"name":"Utilitzar substitucions de text","searchName":"Utilitzar substitucions de text en un document del Pages"},"tanc48ac66bd":{"name":"Crear, eliminar o canviar el nom d’un estil de paràgraf","searchName":"Crear, eliminar o canviar el nom d’estils de paràgraf en un document del Pages"},"tanb3bc78786":{"name":"Imatges","searchName":"Afegir imatges en un document del Pages"},"tan38b1721f0":{"name":"Majúscules + Clic","categories":["aside"]},"tan5e2833bf7":{"name":"Utilitzar guies d’alineació","searchName":"Utilitzar guies d’alineació en un document del Pages"},"tanf610b45cf":{"name":"Seleccionar text i col·locar el punt d’inserció","searchName":"Seleccionar text en un document del Pages"},"tand47165437":{"name":"Mostrar el recompte de paraules i altres estadístiques","searchName":"Mostrar el recompte de paraules i altres estadístiques en un document del Pages"},"tan6704f1b0f":{"name":"Especificar el nom de l’autor i el color del comentari","searchName":"Especificar el nom de l’autor i l’aspecte dels comentaris en un document del Pages"},"tanbfae7ac27":{"name":"punt d’inserció","categories":["aside"]},"tanf709cafed":{"name":"Especificar el tipus de lletra per omissió per als documents","searchName":"Especificar el tipus de lletra per omissió per als documents del Pages"},"tan1d77504d1":{"name":"plantilla","categories":["aside"]},"tan23c9b6406":{"name":"document de disposició de pàgina","categories":["aside"]},"tan1c959548d":{"name":"Ressaltar cel·les condicionalment","searchName":"Afegir ressaltat condicional a les cel·les d’una taula al Pages"},"tan809b4dea8":{"name":"Barra lateral “Comentaris i canvis”","categories":["aside"]},"tane9d8593b0":{"name":"Visió general del Pages"},"tan227ad0c21":{"name":"Veure o canviar els permisos d’un document compartit"},"tanc388a772c":{"name":"Mostrar, ocultar o editar un nom de taula","searchName":"Mostrar, ocultar o editar un nom de taula al Pages"},"tan5394fbf0f":{"name":"Enviar una còpia d’un document","href":"tan5394fbf0f.html"},"tan4745152e4":{"name":"Elevar i abaixar caràcters i text","searchName":"Elevar i abaixar caràcters i text d’un document del Pages"},"tandbcfe3f68":{"name":"Si no podeu eliminar alguna cosa d’un document","searchName":"Si no podeu eliminar alguna cosa d’un document del Pages"},"tanf69e05015":{"name":"Aplicar negreta, cursiva, subratllat o ratllat al text","searchName":"Afegir negreta, cursiva, subratllat o ratllat al text en un document del Pages"},"tanea6d0807d":{"name":"Columnes de text","searchName":"Formatar text en columnes en un document del Pages"},"tan78c0ddfdb":{"name":"Enviar una còpia d’un document","searchName":"Enviar una còpia d’un document del Pages"},"tan014c3bd19":{"name":"Símbols de les dreceres de teclat","href":"tan014c3bd19.html","searchName":"Símbols de les dreceres de teclat del Pages"},"tanc2dcd8bf5":{"name":"Amb el Handoff"},"tanbde221fc8":{"name":"seleccionar text","categories":["aside"]},"tanc422178d0":{"name":"Visió general sobre els objectes"},"tan114930688":{"name":"Canviar de mida, girar i invertir objectes","searchName":"Canviar de mida, girar i invertir objectes en un document del Pages"},"tana91415979":{"name":"Emplenar formes i quadres de text amb un color o una imatge","searchName":"Emplenar una forma o un quadre de text en un document del Pages"},"tan39ebf390a":{"name":"Definir tabuladors","searchName":"Ajustar tabuladors en un document del Pages"},"tancdeedb11c":{"name":"Obrir un document","searchName":"Obrir un document del Pages existent"},"tan72488052":{"name":"Navegació ràpida","searchName":"Navegació ràpida en un document del Pages"},"tan3af7438f2":{"name":"Afegir i editar contingut a les cel·les d’una taula","searchName":"Afegir i editar contingut de les cel·les d’una taula al Pages"},"tan3ac4e1b94":{"name":"Formatar taules per a text bidireccional","searchName":"Formatar taules per a text bidireccional al Pages"},"tanb8470373a":{"name":"Afegir objectes a les cel·les d’una taula","searchName":"Afegir objectes a les cel·les d’una taula al Pages"},"tan3c62ca531":{"name":"Funcions que accepten condicions i comodins com a arguments","searchName":"Funcions del Pages que accepten condicions i comodins com a arguments al Pages"},"tan803495662":{"name":"secció","categories":["aside"]},"tanc87eaca89":{"name":"Ajustar l’espai entre caràcters","searchName":"Ajustar l’espaiat entre caràcters en un document del Pages"},"tanc9ead56b9":{"name":"Col·locar i alinear objectes","searchName":"Col·locar i espaiar objectes en un document del Pages"},"tan37b10e710":{"name":"iCloud","categories":["aside"]},"tan85976ff6b":{"name":"MathType","categories":["aside"]},"tane5bb1a9b6":{"name":"Redimensionar les files i columnes d’una taula","searchName":"Redimensionar les files i columnes d’una taula al Pages"},"tana3148ea61":{"name":"Línies i fletxes","searchName":"Afegir línies i fletxes en un document del Pages"},"tanafa2f718a":{"name":"Personalitzar la barra d’eines","searchName":"Personalitzar la barra d’eines del Pages"},"tanc80345ef4":{"name":"Canviar les línies de retícula i els colors d’una taula"},"tan5836bce3d":{"name":"Canviar el tipus d’un gràfic","searchName":"Canviar un gràfic d’un tipus a un altre al Pages"},"tana41710df7":{"name":"Càlculs","searchName":"Calcular valors al Pages utilitzant les dades de les cel·les d’una taula"},"tan7f1de6ec5":{"name":"Restaurar una versió anterior d’un document","searchName":"Restaurar una versió anterior d’un document del Pages"},"tan7248753e":{"name":"Capçaleres, peus de pàgina i números de pàgina","searchName":"Afegir capçaleres, peus de pàgina i números de pàgina en un document del Pages"},"tan8f54dbbd9":{"name":"Afegir, eliminar o reordenar pàgines","searchName":"Afegir, eliminar o reordenar pàgines en un document del Pages"},"tan42d243e76":{"name":"Actualitzar o revertir un estil de paràgraf","searchName":"Actualitzar o revertir un estil de paràgraf en un document del Pages"},"tan785873ed3":{"name":"Vídeo i àudio","searchName":"Afegir vídeo i àudio en un document del Pages"},"tancfc4d5c02":{"name":"Eliminar un document","searchName":"Eliminar un document del Pages"},"tan9b8d55b94":{"name":"seleccionar cel·les","categories":["aside"]},"tan6df85201f":{"name":"Col·laborar en un document compartit","searchName":"Col·laborar en un document compartit del Pages"},"tanece59000a":{"name":"Personalitzar l’aspecte de les sèries de dades","searchName":"Personalitzar l’aspecte de les sèries de dades en un gràfic al Pages"},"tanc921265e9":{"name":"Afegir o eliminar files i columnes","searchName":"Afegir i canviar files i columnes en una taula del Pages"},"tan8ba5fdcfa":{"name":"Afegir una llegenda, línies de retícula i altres marques","searchName":"Afegir una llegenda, línies de retícula i altres marques al Pages"},"tandb043f1ca":{"name":"Connectar dos objectes amb una línia","searchName":"Connectar objectes amb una línia al Pages"},"tand4b4df5c5":{"name":"Canviar de mida, moure o bloquejar una taula","searchName":"Canviar de mida, moure o bloquejar una taula al Pages"},"tana34daa50":{"name":"Copyright"},"taned4110e43":{"name":"Afegir un efecte de ressaltat al text","searchName":"Afegir un efecte de ressaltat en un document del Pages"},"tan93d2cfcea":{"name":"Control + clic","categories":["aside"]},"tan9efdf9906":{"name":"Bloquejar un document","searchName":"Bloquejar un document del Pages"},"tanb624f904e":{"name":"drecera de teclat","categories":["aside"]},"tan9a3032ccd":{"name":"barra d’eines de revisió","categories":["aside"]},"tan9eb2d52ca":{"name":"Etiqueta","categories":["aside"]},"tanc2e488747":{"name":"Desar un document en un altre format","href":"tanc2e488747.html"},"tan532dc7442":{"name":"Utilitzar estils de gràfic","searchName":"Utilitzar estils de gràfic al Pages"},"tan1bf3352bb":{"name":"selector de plantilles","categories":["aside"]},"tan7aaef6765":{"name":"Crear i utilitzar estils de caràcter","searchName":"Crear i utilitzar estils de caràcter al Pages"},"tan0c9e54229":{"name":"Afegir o eliminar una taula","searchName":"Afegir o eliminar una taula al Pages"},"tan6698de8db":{"name":"Utilitzar estils de taula","searchName":"Utilitzar estils de taula al Pages"},"tanbb81779d8":{"name":"Afegir una vora i un fons a un gràfic"},"tanec2c2fdfd":{"name":"Utilitzar accents i caràcters especials","searchName":"Utilitzar accents i caràcters especials en un document del Pages"},"tan72486d0d":{"name":"Buscar i substituir text","searchName":"Buscar i substituir text en un document del Pages"},"tan0e6bf8310":{"name":"Afegir citacions bibliogràfiques","searchName":"Afegir citacions bibliogràfiques en un document del Pages"},"tan92235a2d6":{"name":"Interlineat","searchName":"Ajustar l’interlineat en un document del Pages"},"tanb07e899b3":{"name":"Afegir o eliminar un gràfic","searchName":"Afegir o eliminar un gràfic al Pages"},"tan1b320e5a8":{"name":"Convidar altres persones a col·laborar en un document","searchName":"Convidar altres persones a col·laborar en un document del Pages"},"tand694c0847":{"name":"Compte de l’iCloud","categories":["aside"]},"tan1aa688b36":{"name":"Crear i gestionar carpetes","searchName":"Crear carpetes per als documents del Pages"},"tan365bd1dea":{"name":"Moure, redimensionar i girar un gràfic","searchName":"Moure, redimensionar i girar un gràfic al Pages"},"tanbb3f4cb":{"name":"Notes a peu de pàgina i notes al final","searchName":"Afegir notes al peu i notes al final en un document del Pages"},"tanf3d8c3e49":{"name":"Revisar l’ortografia","searchName":"Revisar l’ortografia en un document del Pages"},"tan4d7be9bf0":{"name":"On és el meu document?","searchName":"On és el meu document?"},"taneef63d4fa":{"name":"Fusionar o escindir cel·les de taula","searchName":"Fusionar o escindir cel·les de taula al Pages"},"tan802e88b40":{"name":"Afegir vores i línies divisòries","searchName":"Afegir vores i línies divisòries al Pages"},"tanec30c9495":{"name":"sèrie de dades","categories":["aside"]},"tand23f7b5d7":{"name":"Afegir salts de línia, de pàgina i de columna","searchName":"Afegir salts de línia, de pàgina i de columna en un document del Pages"},"tanc416a4b45":{"name":"clauer","categories":["aside"]},"tand8eca23a4":{"name":"barra d’eines","categories":["aside"]},"tan5eab46568":{"name":"Superposar, agrupar i bloquejar objectes","searchName":"Disposar en capes, agrupar i bloquejar objectes en un document del Pages"},"tanecbd98c11":{"name":"barra de dreceres","categories":["aside"]}},"copyright_text":"Copyright © 2016 Apple Inc. Tots els drets reservats."}