{"css":"","framework":"duck-10.1.0","title":"Karten-Hilfe","build_id":"5791a882094622de5f5e6fe5","quick_links":[],"icon":"..\/SharedGlobalArt\/AppIconDefault_Maps.png","sections":{},"birdseed_version":5,"toc":["fir513eb569d","mps724f1a39a","mps4d8a6bd2f","mpsa33caac1f","mpsf81b66a62","mps409c69359","mps940f50a65","mpsa4871840a","mpsaf9c43d8f","mps1eccd51e8","mps36380d1ed"],"locale":"de","version":"10.12","source_schema":"apd-schema","enable_tracking":false,"platform":"mac","build_date":"2016.07.22-01:43:47","landing":"mps0f40a2c9e","product":"maps","urls":{},"copyright":"","show_previous_next":false,"topics":{"mpsa4871840a":{"name":"Sichern von Wegbeschreibung oder Ort zur späteren Verwendung","searchName":"Sichern von Wegbeschreibungen oder Orten zur späteren Verwendung in der App „Karten“ "},"mps724f1a39a":{"name":"Suchen und Freigeben eines Orts","searchName":"Suchen und Freigeben eines Orts in der App „Karten“"},"mps36380d1ed":{"name":"Tastaturkurzbefehle und Gesten"},"mpsad9b5a772":{"name":"Anzeigen des aktuellen Orts","categories":["aside"]},"mps0f40a2c9e":{"name":"Karten-Hilfe","href":"mps0f40a2c9e.html","categories":["landing"]},"mps940f50a65":{"name":"Markieren eines Standorts mit einer Stecknadel","searchName":"Markieren eines Standorts auf einer Karte mit einer Stecknadel"},"mps4d8a6bd2f":{"name":"Abrufen und Senden von Wegbeschreibungen","searchName":"Verwenden der App „Karten“ zum Abrufen von Wegbeschreibungen"},"mpsf81b66a62":{"name":"Suchen einer zuletzt durchgeführten Suche oder Löschen des Suchverlaufs","searchName":"Suchen einer zuletzt durchgeführten Suche oder Löschen des Suchverlaufs in der App „Karten“"},"mpsaf9c43d8f":{"name":"Anpassen der Kartendarstellung"},"mps409c69359":{"name":"Anzeigen der Verkehrslage","searchName":"Anzeigen der Verkehrslage in der App „Karten“"},"mps1eccd51e8":{"name":"Zoomen, Bewegen, dDehen, Nigen","searchName":"Zoomen, Bewegen, Drehen, Neigen in einer Karte"},"fir513eb569d":{"name":"Karten – Übersicht"},"mpsa33caac1f":{"name":"Anzeigen des aktuellen Standorts","searchName":"Anzeigen des aktuellen Standorts in der App „Karten“"}},"copyright_text":"Copyright © 2016 Apple Inc. Alle Rechte vorbehalten."}